{
    "order" : 6,
    "name" : "Get All Building Option",
    "description" : "",
    "request" : {
        "url" : "https://stg-satpam.spacestock.com/office/reader/1.0/buildingoption?page=1&size=999",
        "method" : "GET",
        "headers" : {
            "Authorization" : "{auth.idToken}"
        },
        "payload" : null
    },
    "expect" : {
        "status_code" : 200,
        "headers" : null,
        "evaluate" : []
    },
    "pipeline" : {
        "cache" : false,
        "cache_as" : "",
        "on_failure" : "exit"
    }
}